{"models":{"Materialpassport":{"id":"kjzl6hvfrbw6c826lx8p6h8sbbeoqo6vxytxd3dm4eg9yj3c045htk2t1kbrh5f","accountRelation":{"type":"list"}},"Component":{"id":"kjzl6hvfrbw6c7pjydme0kn8n27odl618lfgc4eturws3vzprtof3jqhxmb7k7p","accountRelation":{"type":"list"}}},"objects":{"Materialpassport":{"name":{"type":"string","required":true},"created":{"type":"string","required":true},"completed":{"type":"boolean","required":true},"author":{"type":"view","viewType":"documentAccount"},"version":{"type":"view","viewType":"documentVersion"}},"Component":{"mpID":{"type":"streamid","required":true},"name":{"type":"string","required":true},"actor":{"type":"reference","refType":"enum","refName":"ComponentActor","required":false},"created":{"type":"string","required":true},"attributes":{"type":"string","required":true},"lifecyclephase":{"type":"reference","refType":"enum","refName":"ComponentLcp","required":false},"functionalLayer":{"type":"reference","refType":"enum","refName":"ComponentFunctionalLayer","required":false},"mp":{"type":"view","viewType":"relation","relation":{"source":"document","model":"kjzl6hvfrbw6c826lx8p6h8sbbeoqo6vxytxd3dm4eg9yj3c045htk2t1kbrh5f","property":"mpID"}},"author":{"type":"view","viewType":"documentAccount"},"version":{"type":"view","viewType":"documentVersion"}}},"enums":{"ComponentActor":["ARCHITECT","CONSTRUCTION_CONTRACTOR","DECONSTRUCTOR","LOGISTIC_MANAGER","MAINTENANCE_CONTRACTOR","PRODUCT_INSTALLER","PRODUCT_MANUFACTURER","PRODUCT_SUPPLIER","PROPERTY_USER"],"ComponentLcp":["DISASSEMBLY","REMANUFACTURING","CONSTRUCTION","ASSEMBLY","DESIGN","MAINTENANCE","MANUFACTURING","OPERATION","REUSE","TRANSPORT_LOGISTIC"],"ComponentFunctionalLayer":["BUILDING","COMPONENT","MATERIAL","MODULE","PRODUCT","STOREY"]},"accountData":{"materialpassportList":{"type":"connection","name":"Materialpassport"},"componentList":{"type":"connection","name":"Component"}}}
